LICENSE
MANIFEST.in
README.md
package.json
setup.py
dash_test/DashTest.py
dash_test/HeatmapLayer.py
dash_test/__init__.py
dash_test/_imports_.py
dash_test/dash_test.min.js
dash_test/dash_test.min.js.map
dash_test/metadata.json
dash_test/package-info.json
dash_test.egg-info/PKG-INFO
dash_test.egg-info/SOURCES.txt
dash_test.egg-info/dependency_links.txt
dash_test.egg-info/top_level.txt