Metadata-Version: 1.1
Name: dash-test
Version: 0.0.2
Summary: Project Description
Home-page: UNKNOWN
Author: fj-blanco <fjavib@gmail.com>
Author-email: UNKNOWN
License: MIT
Platform: UNKNOWN
Classifier: Framework :: Dash
